nudisxs/__about__.py
nudisxs/__init__.py
nudisxs/_nudisxs.cpython-310-x86_64-linux-gnu.so
nudisxs/disxs.py
nudisxs/f_sources/BendFactor.f
nudisxs/f_sources/DISkinematics.f
nudisxs/f_sources/FQCD_L.f
nudisxs/f_sources/F_L.f
nudisxs/f_sources/FunGeM.f
nudisxs/f_sources/GeM.f
nudisxs/f_sources/InpOutUnits.f
nudisxs/f_sources/NucleonStructureFunctions.f
nudisxs/f_sources/PhysMathConstants.f
nudisxs/f_sources/R.f
nudisxs/f_sources/R_E143.f
nudisxs/f_sources/R_Liang.f
nudisxs/f_sources/R_WBA.f
nudisxs/f_sources/Routines.f
nudisxs/f_sources/SF_Liang.f
nudisxs/f_sources/Spline2.f
nudisxs/f_sources/d2sDISCC_dxdy.f
nudisxs/f_sources/d2sDISNC_dxdy.f
nudisxs/f_sources/xDIS.f
nudisxs/f_sources/yDIS.f
nudisxs/integrand_1dx.py
nudisxs/integrand_1dy.py
nudisxs/integrand_2d.py
nudisxs/libDISxs.so
nudisxs/tests/__init__.py
nudisxs/tests/test_dis.py
nudisxs/tests/test_dis_kinematics.py
nudisxs/tests/test_dis_total.py
nudisxs-1.1.2.dist-info/METADATA
nudisxs-1.1.2.dist-info/WHEEL
nudisxs-1.1.2.dist-info/entry_points.txt
nudisxs-1.1.2.dist-info/licenses/LICENSE.txt
nudisxs-1.1.2.dist-info/RECORD
