Metadata-Version: 2.1
Name: nudisxs
Version: 1.1.2
Summary: A python interface to fortran code developed by Vadim A. Naumov and Konstantin Kuzmin, calculating neutrino-nucleon deep inelastic charged/neutral current cross-sections.
Author: Vadim A. Naumov and K. Kuzmin
Maintainer-Email: Dmitry V. Naumov <dmitryvnaumov@gmail.com>
License: MIT License
Classifier: Development Status :: 4 - Beta
Classifier: Programming Language :: Python
Classifier: Programming Language :: Python :: 3.7
Classifier: Programming Language :: Python :: 3.8
Classifier: Programming Language :: Python :: 3.9
Classifier: Programming Language :: Python :: 3.10
Classifier: Programming Language :: Python :: 3.11
Classifier: Programming Language :: Python :: Implementation :: CPython
Classifier: Programming Language :: Python :: Implementation :: PyPy
Project-URL: Home, https://git.jinr.ru/dnaumov/nudisxs
Requires-Python: >=3.7
Requires-Dist: numpy>=1.21
Requires-Dist: vegas
License-File: LICENSE.txt
